kosmorrolib/__init__.py
kosmorrolib/__version__.py
kosmorrolib/core.py
kosmorrolib/dateutil.py
kosmorrolib/enum.py
kosmorrolib/ephemerides.py
kosmorrolib/events.py
kosmorrolib/exceptions.py
kosmorrolib/model.py
kosmorrolib-1.0.13.dist-info/METADATA
kosmorrolib-1.0.13.dist-info/WHEEL
kosmorrolib-1.0.13.dist-info/licenses/LICENSE.md
kosmorrolib-1.0.13.dist-info/RECORD
