Metadata-Version: 2.4
Name: kosmorrolib
Version: 1.0.13
Summary: A library to computes the ephemerides.
License: AGPL-3.0-or-later
License-File: LICENSE.md
Keywords: kosmorro,astronomy,ephemerides,ephemeris
Author: Jérôme Deuchnord
Author-email: jerome@deuchnord.fr
Requires-Python: >=3.8,<4.0
Classifier: Development Status :: 5 - Production/Stable
Classifier: Intended Audience :: Developers
Classifier: Intended Audience :: Education
Classifier: License :: OSI Approved :: GNU Affero General Public License v3 or later (AGPLv3+)
Classifier: Programming Language :: Python :: 3
Classifier: Programming Language :: Python :: 3.8
Classifier: Programming Language :: Python :: 3.9
Classifier: Programming Language :: Python :: 3.10
Classifier: Programming Language :: Python :: 3.11
Classifier: Programming Language :: Python :: 3.12
Classifier: Programming Language :: Python :: 3.13
Classifier: Programming Language :: Python :: 3.14
Classifier: Topic :: Scientific/Engineering :: Astronomy
Classifier: Topic :: Software Development :: Libraries :: Python Modules
Requires-Dist: numpy (<1.25) ; python_version == "3.8"
Requires-Dist: numpy (<2.1) ; python_version == "3.9"
Requires-Dist: numpy (<2.3) ; python_version == "3.10"
Requires-Dist: numpy (>=2.3,<3.0) ; python_version >= "3.11"
Requires-Dist: python-dateutil (>=2.8,<3.0)
Requires-Dist: skyfield (>=1.49,<2.0)
Requires-Dist: skyfield-data
Project-URL: Documentation, https://kosmorro.space/lib/doc
Project-URL: Homepage, https://kosmorro.space/lib
Project-URL: Repository, https://github.com/Kosmorro/lib
